dataset_grouper/__init__.py
dataset_grouper/beam_transforms.py
dataset_grouper/count_utils.py
dataset_grouper/data_loaders.py
dataset_grouper/serialization.py
dataset_grouper/test_utils.py
dataset_grouper/tf_utils.py
dataset_grouper/tfds_pipelines.py
dataset_grouper/types.py
dataset_grouper-0.3.0.dist-info/LICENSE
dataset_grouper-0.3.0.dist-info/METADATA
dataset_grouper-0.3.0.dist-info/WHEEL
dataset_grouper-0.3.0.dist-info/top_level.txt
dataset_grouper-0.3.0.dist-info/RECORD
