Metadata-Version: 2.1
Name: dataset_grouper
Version: 0.3.0
Summary: Dataset Grouper - A library for datasets with group-level structure.
Author-email: Dataset Grouper Team <dataset-grouper-dev@google.com>
License: 
Project-URL: Homepage, https://github.com/google-research/dataset_grouper
Project-URL: Repository, https://github.com/google-research/dataset_grouper
Project-URL: Changelog, https://github.com/google-research/dataset_grouper/blob/main/CHANGELOG.md
Keywords: federated learning,datasets,machine learning
Classifier: License :: OSI Approved :: Apache Software License
Classifier: Intended Audience :: Science/Research
Requires-Python: >=3.10
License-File: LICENSE
Requires-Dist: apache-beam >=2.47.0
Requires-Dist: numpy ~=1.21
Requires-Dist: tensorflow ~=2.12.0
Requires-Dist: tensorflow-datasets ~=4.9.0
